{
    "game_settings": {
        "window_height": 400,
        "window_width": 800,
        "fps": 60
    },
    "world_settings": {
        "gravity": 10
    },
    "player": {
        "player_width": 50,
        "player_height": 50,
        "player_x": 200,
        "player_y": 60,
        "player_speed_x": 5,
        "player_speed_y": 5,
        "color": "Red",
        "background_color": "Black",
        "player_max_jump": 150
    },
    "map": {
        "background": {
            "background_color": "White"
        },
        "floor":{
            "floor_x": 0,
            "floor_y": 10,
            "floor_height": 10,
            "floor_width": 1000,
            "color": "Green"
        }
    }
}